Metadata-Version: 1.2
Name: async-Eel
Version: 1.0b1
Summary: For little HTML GUI applications, with easy Python/JS interop
Home-page: UNKNOWN
Author: Chris Knott
Author-email: chrisknott@hotmail.co.uk
License: UNKNOWN
Keywords: gui,html,javascript,electron
Platform: UNKNOWN
Requires-Python: >=3.6
